{
    "AX(CDD)": {
        "error": 7.965121306287422e-06,
        "error_type": "SEM",
        "filter_outliers_dict": {
            "filter_outliers": true,
            "iterations": 1,
            "std_devs": 2
        },
        "fit": "average",
        "modifier_error": 1.1400592727757444e-05,
        "modifier_value": 5.1336275043017554e-05,
        "value": 8.037530568728994e-05
    },
    "H1": {
        "error": 0.006507090578371654,
        "error_type": "SEM",
        "filter_outliers_dict": {
            "filter_outliers": true,
            "iterations": 1,
            "std_devs": 2
        },
        "fit": "average",
        "modifier_error": 0.0,
        "modifier_value": 0.0,
        "value": -0.013342916657985428
    },
    "H2": {
        "error": 0.014653915580947554,
        "error_type": "SEM",
        "filter_outliers_dict": {
            "filter_outliers": true,
            "iterations": 1,
            "std_devs": 2
        },
        "fit": "average",
        "modifier_error": 0.0,
        "modifier_value": 0.0,
        "value": 0.3312141492551386
    },
    "L1": {
        "error": 0.0059108676290565145,
        "error_type": "SEM",
        "filter_outliers_dict": {
            "filter_outliers": true,
            "iterations": 1,
            "std_devs": 2
        },
        "fit": "average",
        "modifier_error": 0.0,
        "modifier_value": 0.0,
        "value": -0.010350013420078033
    },
    "L2(CDD)": {
        "error": 1.1027429696791495e-22,
        "error_type": "SEM",
        "filter_outliers_dict": {
            "filter_outliers": true,
            "iterations": 1,
            "std_devs": 10
        },
        "fit": "average",
        "modifier_error": 3.0163133156377696e-06,
        "modifier_value": 3.5935392530112287e-06,
        "value": 3.593539253011228e-06
    }
}