{
    "Ar36": {
        "error": 0.00024718827187455127,
        "error_type": "",
        "fit": "previous",
        "references": [
            {
                "exclude": false,
                "record_id": "bc-03-J-2642"
            }
        ],
        "value": 0.014292838934940655
    },
    "Ar37": {
        "error": 0.004834363238673497,
        "error_type": "",
        "fit": "previous",
        "references": [
            {
                "exclude": false,
                "record_id": "bc-03-J-2642"
            }
        ],
        "value": 0.05367843017666729
    },
    "Ar38": {
        "error": 0.0036598430717249475,
        "error_type": "",
        "fit": "previous",
        "references": [
            {
                "exclude": false,
                "record_id": "bc-03-J-2642"
            }
        ],
        "value": 0.03912679419543098
    },
    "Ar39": {
        "error": 0.00860656982999391,
        "error_type": "",
        "fit": "previous",
        "references": [
            {
                "exclude": false,
                "record_id": "bc-03-J-2642"
            }
        ],
        "value": 0.07551390112274789
    },
    "Ar40": {
        "error": 0.006756172022560643,
        "error_type": "",
        "fit": "previous",
        "references": [
            {
                "exclude": false,
                "record_id": "bc-03-J-2642"
            }
        ],
        "value": 0.44616253361358543
    },
    "Ar41": {
        "error": 0.003026086378260087,
        "error_type": "",
        "fit": "previous",
        "references": [
            {
                "exclude": false,
                "record_id": "bc-03-J-2642"
            }
        ],
        "value": 0.04552359824433164
    }
}