{
    "Ar36": {
        "error": 0.00036373251776026545,
        "error_type": "SEM",
        "filter_outliers_dict": {
            "filter_outliers": true,
            "iterations": 2,
            "std_devs": 2,
            "use_iqr_filtering": false,
            "use_standard_deviation_filtering": false
        },
        "fit": "linear",
        "fn": 314,
        "include_baseline_error": true,
        "n": 340,
        "outlier_excluded": [
            130,
            269,
            142,
            271,
            16,
            23,
            158,
            31,
            36,
            294,
            169,
            307,
            309,
            311,
            184,
            312,
            186,
            313,
            321,
            193,
            66,
            199,
            204,
            209,
            235,
            108
        ],
        "reviewed": true,
        "user_excluded": [],
        "value": 0.08282088104645569
    },
    "Ar37": {
        "error": 0.007168960201987593,
        "error_type": "SEM",
        "filter_outliers_dict": {
            "filter_outliers": true,
            "iterations": 2,
            "std_devs": 2,
            "use_iqr_filtering": false,
            "use_standard_deviation_filtering": false
        },
        "fit": "linear",
        "fn": 318,
        "include_baseline_error": true,
        "n": 340,
        "outlier_excluded": [
            9,
            14,
            20,
            276,
            285,
            291,
            169,
            305,
            50,
            51,
            309,
            54,
            314,
            188,
            322,
            75,
            337,
            339,
            241,
            243,
            117,
            119
        ],
        "reviewed": true,
        "user_excluded": [],
        "value": 3.7310876068076677
    },
    "Ar38": {
        "error": 0.0002785336272418761,
        "error_type": "SEM",
        "filter_outliers_dict": {
            "filter_outliers": true,
            "iterations": 2,
            "std_devs": 2,
            "use_iqr_filtering": false,
            "use_standard_deviation_filtering": false
        },
        "fit": "linear",
        "fn": 316,
        "include_baseline_error": true,
        "n": 340,
        "outlier_excluded": [
            258,
            133,
            9,
            13,
            271,
            272,
            145,
            27,
            283,
            45,
            175,
            178,
            180,
            184,
            61,
            321,
            327,
            80,
            210,
            92,
            104,
            107,
            241,
            247
        ],
        "reviewed": true,
        "user_excluded": [],
        "value": 0.04170330796512092
    },
    "Ar39": {
        "error": 0.0072612506096146265,
        "error_type": "SEM",
        "filter_outliers_dict": {
            "filter_outliers": true,
            "iterations": 2,
            "std_devs": 2,
            "use_iqr_filtering": false,
            "use_standard_deviation_filtering": false
        },
        "fit": "linear",
        "fn": 323,
        "include_baseline_error": true,
        "n": 340,
        "outlier_excluded": [
            66,
            132,
            292,
            326,
            231,
            107,
            331,
            237,
            207,
            271,
            18,
            306,
            52,
            181,
            19,
            23,
            50
        ],
        "reviewed": true,
        "user_excluded": [],
        "value": 1.5276351950131195
    },
    "Ar40": {
        "error": 0.03131799859644786,
        "error_type": "SEM",
        "filter_outliers_dict": {
            "filter_outliers": true,
            "iterations": 2,
            "std_devs": 2,
            "use_iqr_filtering": false,
            "use_standard_deviation_filtering": false
        },
        "fit": "parabolic",
        "fn": 316,
        "include_baseline_error": true,
        "n": 340,
        "outlier_excluded": [
            256,
            4,
            5,
            8,
            10,
            143,
            152,
            32,
            36,
            292,
            167,
            306,
            311,
            184,
            320,
            194,
            68,
            203,
            211,
            92,
            99,
            234,
            115,
            244
        ],
        "reviewed": true,
        "user_excluded": [],
        "value": 41.08085553170188
    }
}